mrs_spellings/__init__.py
mrs_spellings/mrs_spellings.py
mrs_spellings/qwerty_caches/__init__.py
mrs_spellings/qwerty_caches/cache_building.ipynb
mrs_spellings/qwerty_caches/closest_cache.py
mrs_spellings/qwerty_caches/closest_dists_cache.py
mrs_spellings/qwerty_caches/dists_cache.py
mrs_spellings/qwerty_caches/qwerty_positions.py
mrs_spellings-1.0.3.dist-info/LICENSE
mrs_spellings-1.0.3.dist-info/WHEEL
mrs_spellings-1.0.3.dist-info/METADATA
mrs_spellings-1.0.3.dist-info/RECORD
