Metadata-Version: 2.1
Name: mrs-spellings
Version: 1.0.3
Summary: a micro utility for generating plausible misspellings
Home-page: https://github.com/CircArgs/mrs_spellings
License: MIT
Author: CircArgs
Author-email: quebecname@gmail.com
Requires-Python: >=3.6,<4.0
Classifier: License :: OSI Approved :: MIT License
Classifier: Programming Language :: Python :: 3
Classifier: Programming Language :: Python :: 3.6
Classifier: Programming Language :: Python :: 3.7
Classifier: Programming Language :: Python :: 3.8
